{
	"info": {
		"_postman_id": "b38e82a1-58fa-45f2-9093-9da6adab6e3d",
		"name": "人人影视API",
		"schema": "https://schema.getpostman.com/json/collection/v2.1.0/collection.json"
	},
	"item": [
		{
			"name": "index",
			"request": {
				"method": "GET",
				"header": [
					{
						"key": "Accept-Encoding",
						"value": "gzip"
					},
					{
						"key": "Connection",
						"value": "Keep-Alive"
					},
					{
						"key": "User-Agent",
						"value": "okhttp/3.5.0"
					}
				],
				"url": {
					"raw": "mobil.allappapi.com/index.php?accesskey=519fc5ab85c8015b175449477561a827&client=2&a=index&m=index&tlimit=10&g=api/v1&alimit=10",
					"host": [
						"mobil",
						"allappapi",
						"com"
					],
					"path": [
						"index.php"
					],
					"query": [
						{
							"key": "accesskey",
							"value": "519fc5ab85c8015b175449477561a827"
						},
						{
							"key": "client",
							"value": "2"
						},
						{
							"key": "a",
							"value": "index"
						},
						{
							"key": "m",
							"value": "index"
						},
						{
							"key": "tlimit",
							"value": "10"
						},
						{
							"key": "g",
							"value": "api/v1"
						},
						{
							"key": "alimit",
							"value": "10"
						}
					]
				}
			},
			"response": []
		},
		{
			"name": "resource_item",
			"request": {
				"method": "GET",
				"header": [
					{
						"key": "Connection",
						"value": "Keep-Alive"
					},
					{
						"key": "Accept-Encoding",
						"value": "gzip"
					},
					{
						"key": "User-Agent",
						"value": "okhttp/3.5.0"
					}
				],
				"url": {
					"raw": "mobil.allappapi.com/index.php?accesskey=519fc5ab85c8015b175449477561a827&client=2&a=resource_item&season=102&m=index&episode=2&id=36138&g=api/v1",
					"host": [
						"mobil",
						"allappapi",
						"com"
					],
					"path": [
						"index.php"
					],
					"query": [
						{
							"key": "accesskey",
							"value": "519fc5ab85c8015b175449477561a827"
						},
						{
							"key": "client",
							"value": "2"
						},
						{
							"key": "a",
							"value": "resource_item"
						},
						{
							"key": "season",
							"value": "102"
						},
						{
							"key": "m",
							"value": "index"
						},
						{
							"key": "episode",
							"value": "2"
						},
						{
							"key": "id",
							"value": "36138"
						},
						{
							"key": "g",
							"value": "api/v1"
						}
					]
				}
			},
			"response": []
		},
		{
			"name": "resource",
			"request": {
				"method": "GET",
				"header": [
					{
						"key": "Connection",
						"value": "Keep-Alive"
					},
					{
						"key": "Accept-Encoding",
						"value": "gzip"
					},
					{
						"key": "User-Agent",
						"value": "okhttp/3.5.0"
					}
				],
				"url": {
					"raw": "mobil.allappapi.com/index.php?accesskey=519fc5ab85c8015b175449477561a827&client=2&a=resource&m=index&id=35760&g=api/v1",
					"host": [
						"mobil",
						"allappapi",
						"com"
					],
					"path": [
						"index.php"
					],
					"query": [
						{
							"key": "accesskey",
							"value": "519fc5ab85c8015b175449477561a827"
						},
						{
							"key": "client",
							"value": "2"
						},
						{
							"key": "a",
							"value": "resource"
						},
						{
							"key": "m",
							"value": "index"
						},
						{
							"key": "id",
							"value": "35760"
						},
						{
							"key": "g",
							"value": "api/v1"
						}
					]
				}
			},
			"response": []
		},
		{
			"name": "search",
			"request": {
				"method": "GET",
				"header": [
					{
						"key": "Connection",
						"value": "Keep-Alive"
					},
					{
						"key": "Accept-Encoding",
						"value": "gzip"
					},
					{
						"key": "User-Agent",
						"value": "okhttp/3.5.0"
					}
				],
				"url": {
					"raw": "mobil.allappapi.com/index.php?accesskey=519fc5ab85c8015b175449477561a827&client=2&a=search&st=resource&page=1&g=api/v1&k=蓝色星球&limit=5",
					"host": [
						"mobil",
						"allappapi",
						"com"
					],
					"path": [
						"index.php"
					],
					"query": [
						{
							"key": "accesskey",
							"value": "519fc5ab85c8015b175449477561a827"
						},
						{
							"key": "client",
							"value": "2"
						},
						{
							"key": "a",
							"value": "search"
						},
						{
							"key": "st",
							"value": "resource",
							"description": "resource|article"
						},
						{
							"key": "page",
							"value": "1"
						},
						{
							"key": "g",
							"value": "api/v1"
						},
						{
							"key": "k",
							"value": "蓝色星球"
						},
						{
							"key": "limit",
							"value": "5"
						}
					]
				}
			},
			"response": []
		},
		{
			"name": "resource_list",
			"request": {
				"method": "GET",
				"header": [],
				"url": {
					"raw": "mobil.allappapi.com/index.php?accesskey=519fc5ab85c8015b175449477561a827&client=2&a=resource_list&g=api%2Fv1&area=&sort=update&page=1&channel=&year=&limit=30",
					"host": [
						"mobil",
						"allappapi",
						"com"
					],
					"path": [
						"index.php"
					],
					"query": [
						{
							"key": "accesskey",
							"value": "519fc5ab85c8015b175449477561a827"
						},
						{
							"key": "client",
							"value": "2"
						},
						{
							"key": "a",
							"value": "resource_list"
						},
						{
							"key": "g",
							"value": "api%2Fv1"
						},
						{
							"key": "area",
							"value": ""
						},
						{
							"key": "sort",
							"value": "update"
						},
						{
							"key": "page",
							"value": "1"
						},
						{
							"key": "channel",
							"value": ""
						},
						{
							"key": "year",
							"value": ""
						},
						{
							"key": "limit",
							"value": "30"
						}
					]
				}
			},
			"response": []
		},
		{
			"name": "article_list",
			"request": {
				"method": "GET",
				"header": [],
				"url": {
					"raw": "mobil.allappapi.com/index.php?accesskey=519fc5ab85c8015b175449477561a827&client=2&a=article_list&g=api/v1&page=2",
					"host": [
						"mobil",
						"allappapi",
						"com"
					],
					"path": [
						"index.php"
					],
					"query": [
						{
							"key": "accesskey",
							"value": "519fc5ab85c8015b175449477561a827"
						},
						{
							"key": "client",
							"value": "2"
						},
						{
							"key": "a",
							"value": "article_list"
						},
						{
							"key": "g",
							"value": "api/v1"
						},
						{
							"key": "page",
							"value": "2"
						}
					]
				}
			},
			"response": []
		},
		{
			"name": "article",
			"request": {
				"method": "GET",
				"header": [],
				"url": {
					"raw": "mobil.allappapi.com/index.php?accesskey=519fc5ab85c8015b175449477561a827&client=2&a=article&g=api/v1&id=31551",
					"host": [
						"mobil",
						"allappapi",
						"com"
					],
					"path": [
						"index.php"
					],
					"query": [
						{
							"key": "accesskey",
							"value": "519fc5ab85c8015b175449477561a827"
						},
						{
							"key": "client",
							"value": "2"
						},
						{
							"key": "a",
							"value": "article"
						},
						{
							"key": "g",
							"value": "api/v1"
						},
						{
							"key": "id",
							"value": "31551",
							"description": "31538(包含extend 节点)"
						}
					]
				}
			},
			"response": []
		},
		{
			"name": "article_extend",
			"request": {
				"method": "GET",
				"header": [],
				"url": {
					"raw": "http://api1.ousns.net/index.php?accesskey=519fc5ab85c8015b175449477561a827&client=2&a=article&id=31538&g=api/v1",
					"protocol": "http",
					"host": [
						"api1",
						"ousns",
						"net"
					],
					"path": [
						"index.php"
					],
					"query": [
						{
							"key": "accesskey",
							"value": "519fc5ab85c8015b175449477561a827"
						},
						{
							"key": "client",
							"value": "2"
						},
						{
							"key": "a",
							"value": "article"
						},
						{
							"key": "id",
							"value": "31538",
							"description": "31538"
						},
						{
							"key": "g",
							"value": "api/v1"
						}
					]
				}
			},
			"response": []
		},
		{
			"name": "resource_pc",
			"request": {
				"method": "GET",
				"header": [],
				"url": {
					"raw": "http://pc.zmzapi.com/index.php?g=api/pv2&m=index&a=resource&accesskey=519f9cab85c8059d17544947k361a827&id=11057",
					"protocol": "http",
					"host": [
						"pc",
						"zmzapi",
						"com"
					],
					"path": [
						"index.php"
					],
					"query": [
						{
							"key": "g",
							"value": "api/pv2"
						},
						{
							"key": "m",
							"value": "index"
						},
						{
							"key": "a",
							"value": "resource"
						},
						{
							"key": "accesskey",
							"value": "519f9cab85c8059d17544947k361a827"
						},
						{
							"key": "id",
							"value": "11057"
						}
					]
				}
			},
			"response": []
		},
		{
			"name": "comment_list",
			"request": {
				"method": "GET",
				"header": [],
				"url": {
					"raw": "http://pc.zmzapi.com/index.php?g=api/pv3&m=index&client=5&accesskey=519f9cab85c8059d17544947k361a827&a=comments_list&limit=10&page=1&uid=&token=&channel=tv&itemid=40595",
					"protocol": "http",
					"host": [
						"pc",
						"zmzapi",
						"com"
					],
					"path": [
						"index.php"
					],
					"query": [
						{
							"key": "g",
							"value": "api/pv3"
						},
						{
							"key": "m",
							"value": "index"
						},
						{
							"key": "client",
							"value": "5"
						},
						{
							"key": "accesskey",
							"value": "519f9cab85c8059d17544947k361a827"
						},
						{
							"key": "a",
							"value": "comments_list"
						},
						{
							"key": "limit",
							"value": "10"
						},
						{
							"key": "page",
							"value": "1"
						},
						{
							"key": "uid",
							"value": ""
						},
						{
							"key": "token",
							"value": ""
						},
						{
							"key": "channel",
							"value": "tv"
						},
						{
							"key": "itemid",
							"value": "40595"
						}
					]
				}
			},
			"response": []
		}
	]
}